__init__.py
toolpy_buddy/__init__.py
toolpy_buddy/cloud/__init__.py
toolpy_buddy/cloud/azure.py
toolpy_buddy/cloud/graph.py
toolpy_buddy/data_processing/dataframe.py
toolpy_buddy/environment/__init__.py
toolpy_buddy/environment/env.py
toolpy_buddy-0.0.7.dist-info/LICENSE
toolpy_buddy-0.0.7.dist-info/METADATA
toolpy_buddy-0.0.7.dist-info/WHEEL
toolpy_buddy-0.0.7.dist-info/top_level.txt
toolpy_buddy-0.0.7.dist-info/RECORD
